{"id": "_importlib_modulespec", "path": "/home/solly/anaconda3/lib/python3.7/site-packages/mypy/typeshed/stdlib/3/_importlib_modulespec.pyi", "mtime": 1547482086, "size": 1595, "hash": "983c757b2117283912173fcab8347d46", "data_mtime": 1547481870, "deps_mtime": null, "dependencies": ["abc", "sys", "typing", "builtins"], "suppressed": [], "child_modules": [], "options": {"always_false": [], "disallow_any_unimported": false, "strict_optional": true, "no_implicit_optional": true, "warn_no_return": true, "disallow_untyped_calls": true, "strict_optional_whitelist": null, "disallow_any_explicit": false, "disallow_incomplete_defs": true, "show_none_errors": true, "check_untyped_defs": true, "always_true": [], "disallow_any_expr": false, "follow_imports": "silent", "platform": "linux", "disallow_any_decorated": false, "warn_unused_ignores": true, "disallow_untyped_decorators": true, "quick_and_dirty": false, "bazel": false, "allow_untyped_globals": false, "disallow_untyped_defs": false, "disallow_any_generics": true, "plugins": [], "mypyc": false, "ignore_errors": false, "disallow_subclassing_any": true, "ignore_missing_imports": false, "follow_imports_for_stubs": false, "warn_return_any": true, "local_partial_types": false}, "dep_prios": [5, 10, 5, 5], "dep_lines": [8, 9, 10, 1], "interface_hash": "bb4d79b4840be70c7354d2d0a9fb33c5", "version_id": "0.650", "ignore_all": true}
